napari_process_points_and_surfaces/__init__.py
napari_process_points_and_surfaces/_quantification.py
napari_process_points_and_surfaces/_surface_annotation_widget.py
napari_process_points_and_surfaces/_utils.py
napari_process_points_and_surfaces/_vedo.py
napari_process_points_and_surfaces/_tests/__init__.py
napari_process_points_and_surfaces/_tests/test_function.py
napari_process_points_and_surfaces/_tests/test_open3d.py
napari_process_points_and_surfaces/_tests/test_vedo_functions.py
napari_process_points_and_surfaces/data/bun_zipper.ply
napari_process_points_and_surfaces/data/bun_zipper_stanford_bunny_source.txt
napari_process_points_and_surfaces/data/gastruloid.ply
napari_process_points_and_surfaces/data/gastruloid_source.txt
napari_process_points_and_surfaces/data/knot.ply
napari_process_points_and_surfaces/data/knot_license.md
napari_process_points_and_surfaces-0.5.0.dist-info/LICENSE
napari_process_points_and_surfaces-0.5.0.dist-info/METADATA
napari_process_points_and_surfaces-0.5.0.dist-info/WHEEL
napari_process_points_and_surfaces-0.5.0.dist-info/entry_points.txt
napari_process_points_and_surfaces-0.5.0.dist-info/top_level.txt
napari_process_points_and_surfaces-0.5.0.dist-info/RECORD
