Metadata-Version: 2.1
Name: napari-process-points-and-surfaces
Version: 0.5.0
Summary: Process and analyze surfaces using open3d and vedo in napari
Home-page: https://github.com/haesleinhuepf/napari-process-points-and-surfaces
Author: Robert Haase, Johannes Soltwedel
Author-email: robert.haase@tu-dresden.de
License: BSD-3-Clause
Project-URL: Bug Tracker, https://github.com/haesleinhuepf/napari-process-points-and-surfaces/issues
Project-URL: Documentation, https://github.com/haesleinhuepf/napari-process-points-and-surfaces#README.md
Project-URL: Source Code, https://github.com/haesleinhuepf/napari-process-points-and-surfaces
Project-URL: User Support, https://github.com/haesleinhuepf/napari-process-points-and-surfaces/issues
Classifier: Development Status :: 2 - Pre-Alpha
Classifier: Intended Audience :: Science/Research
Classifier: Framework :: napari
Classifier: Topic :: Scientific/Engineering :: Image Processing
Classifier: Topic :: Scientific/Engineering :: Information Analysis
Classifier: Programming Language :: Python
Classifier: Programming Language :: Python :: 3
Classifier: Programming Language :: Python :: 3.8
Classifier: Programming Language :: Python :: 3.9
Classifier: Operating System :: OS Independent
Classifier: License :: OSI Approved :: BSD License
Requires-Python: >=3.7
License-File: LICENSE
Requires-Dist: napari-plugin-engine (>=0.1.4)
Requires-Dist: numpy
Requires-Dist: napari
Requires-Dist: napari-tools-menu (>=0.1.14)
Requires-Dist: napari-time-slicer (>=0.4.5)
Requires-Dist: napari-workflows (>=0.2.3)
Requires-Dist: vedo (>=2022.4.1)
Requires-Dist: napari-skimage-regionprops (>=0.5.5)
Requires-Dist: pandas
Requires-Dist: imageio (!=2.22.1)
Requires-Dist: stackview (>=0.5.2)
